jm_base_data_cbase.cpython-38-i386-linux-gnu.so
jm_base_data_cbase-1.0.7.dist-info/RECORD
jm_base_data_cbase-1.0.7.dist-info/LICENSE
jm_base_data_cbase-1.0.7.dist-info/WHEEL
jm_base_data_cbase-1.0.7.dist-info/METADATA
jm_base_data_cbase-1.0.7.dist-info/top_level.txt
